{
  "criterias": [
    "Audited?",
    "Available on Linux?",
    "Available on Mac?",
    "Available on Windows?",
    "Available on Android?",
    "Available in F-Droid?",
    "Available on iOS?",
    "Decentralized?",
    "Additional notes?"
  ],
  "tools": {
    "signal": {
      "name": "Signal",
      "values": {
        "Audited?": "Yes",
        "Available on Linux?": "Yes",
        "Available on Mac?": "Yes",
        "Available on Windows?": "Yes",
        "Available on Android?": "Yes",
        "Available in F-Droid?": "No",
        "Available on iOS?": "Yes",
        "Decentralized?": "No",
        "Additional notes?": ["Phone number required for signup"]
      }
    },
    "simplex": {
      "name": "SimpleX",
      "values": {
        "Audited?": "Yes",
        "Available on Linux?": "Yes",
        "Available on Mac?": "Yes",
        "Available on Windows?": "Yes",
        "Available on Android?": "Yes",
        "Available in F-Droid?": "Yes",
        "Available on iOS?": "Yes",
        "Decentralized?": "Yes",
        "Additional notes?": ["Early in development"]
      }
    },
    "threema": {
      "name": "Threema",
      "values": {
        "Audited?": "Yes",
        "Available on Linux?": "In beta",
        "Available on Mac?": "In beta",
        "Available on Windows?": "In beta",
        "Available on Android?": "Yes",
        "Available in F-Droid?": "No",
        "Available on iOS?": "Yes",
        "Decentralized?": "No",
        "Additional notes?": ["Not free"]
      }
    }
  }
}
