[
  {
    "name": "Coded Bias",
    "link": "https://www.codedbias.com/"
  },
  {
    "name": "The Great Hack",
    "link": "https://www.netflix.com/title/80117542"
  },
  {
    "name": "Nothing to Hide",
    "link": "https://youtu.be/M3mQu9YQesk"
  },
  {
    "name": "The Perfect Weapon",
    "link": "https://www.hbo.com/movies/the-perfect-weapon"
  },
  {
    "name": "The Social Dilemma",
    "link": "https://www.thesocialdilemma.com/"
  },
  {
    "name": "Terms and Conditions May Apply",
    "link": "https://en.wikipedia.org/wiki/Terms_and_Conditions_May_Apply"
  }
]
